[
  {
    "shopName": "tennis",
    "contactPerson": "tennis",
    "phoneNumber": "+44 7352678299",
    "email": "tennisraja62@gmail.com",
    "deliveryAddress": "gos ford street",
    "postcode": "cv1 5de",
    "deliveryDate": "2026-07-06",
    "notes": "",
    "items": [
      {
        "product": {
          "id": "1516",
          "name": "Total",
          "category": "Groceries",
          "size": "1 unit",
          "price": 0,
          "stock": 10731,
          "inStock": true
        },
        "quantity": 1
      },
      {
        "product": {
          "id": "730",
          "name": "KATHIR MALABAR MURUKU 150GM",
          "category": "Snacks & Sweets",
          "size": "150 gm",
          "price": 1.59,
          "stock": 112,
          "inStock": true
        },
        "quantity": 1
      },
      {
        "product": {
          "id": "1516",
          "name": "Total",
          "category": "Groceries",
          "size": "1 unit",
          "price": 0,
          "stock": 10731,
          "inStock": true
        },
        "quantity": 1
      },
      {
        "product": {
          "id": "741",
          "name": "Kathir Toor Dhal (Naden Sambar Parupu) 1+1",
          "category": "Lentils & Pulses",
          "size": "1 unit",
          "price": 6.99,
          "stock": 970,
          "inStock": true
        },
        "quantity": 1
      },
      {
        "product": {
          "id": "1516",
          "name": "Total",
          "category": "Groceries",
          "size": "1 unit",
          "price": 0,
          "stock": 10731,
          "inStock": true
        },
        "quantity": 1
      },
      {
        "product": {
          "id": "1516",
          "name": "Total",
          "category": "Groceries",
          "size": "1 unit",
          "price": 0,
          "stock": 10731,
          "inStock": true
        },
        "quantity": 1
      },
      {
        "product": {
          "id": "741",
          "name": "Kathir Toor Dhal (Naden Sambar Parupu) 1+1",
          "category": "Lentils & Pulses",
          "size": "1 unit",
          "price": 6.99,
          "stock": 970,
          "inStock": true
        },
        "quantity": 1
      },
      {
        "product": {
          "id": "741",
          "name": "Kathir Toor Dhal (Naden Sambar Parupu) 1+1",
          "category": "Lentils & Pulses",
          "size": "1 unit",
          "price": 6.99,
          "stock": 970,
          "inStock": true
        },
        "quantity": 1
      },
      {
        "product": {
          "id": "741",
          "name": "Kathir Toor Dhal (Naden Sambar Parupu) 1+1",
          "category": "Lentils & Pulses",
          "size": "1 unit",
          "price": 6.99,
          "stock": 970,
          "inStock": true
        },
        "quantity": 1
      }
    ],
    "totalBoxes": 9,
    "status": "pending",
    "createdAt": "2026-07-05T12:50:29.962Z",
    "_id": "ORD-1783255829962-ex1bom1i7"
  },
  {
    "shopName": "Test Shop Ltd",
    "contactPerson": "John Doe",
    "phoneNumber": "+44 (0) 1925 123456",
    "email": "test@example.com",
    "deliveryAddress": "123 Test Street, London",
    "postcode": "CV1 5DE",
    "deliveryDate": "2026-07-06",
    "notes": "Test order",
    "items": [
      {
        "product": {
          "id": "1",
          "name": "Test Product",
          "category": "Test",
          "price": 10
        },
        "quantity": 1
      }
    ],
    "_id": "ORD-1783256122458-xlstwx3m5",
    "createdAt": "2026-07-05T12:55:22.459Z",
    "status": "pending"
  }
]